{
  "version": 2,
  "type": "note-aligned",
  "pages": {
    "1": [
      {
        "noteIdx": 1,
        "chord": "G"
      },
      {
        "noteIdx": 5,
        "chord": "Dm"
      },
      {
        "noteIdx": 9,
        "chord": "F"
      },
      {
        "noteIdx": 13,
        "chord": "Dm"
      },
      {
        "noteIdx": 38,
        "chord": "D"
      },
      {
        "noteIdx": 78,
        "chord": "A"
      },
      {
        "noteIdx": 117,
        "chord": "A9"
      },
      {
        "noteIdx": 152,
        "chord": "A"
      },
      {
        "noteIdx": 163,
        "chord": "D"
      },
      {
        "noteIdx": 192,
        "chord": "E"
      },
      {
        "noteIdx": 202,
        "chord": "Gm"
      },
      {
        "noteIdx": 231,
        "chord": "Dm"
      },
      {
        "noteIdx": 235,
        "chord": "C"
      },
      {
        "noteIdx": 239,
        "chord": "Dm"
      },
      {
        "noteIdx": 278,
        "chord": "B"
      }
    ]
  }
}
