{
  "version": 2,
  "type": "note-aligned",
  "pages": {
    "1": [
      {
        "noteIdx": 4,
        "chord": "E"
      },
      {
        "noteIdx": 8,
        "chord": "G"
      },
      {
        "noteIdx": 13,
        "chord": "G"
      },
      {
        "noteIdx": 25,
        "chord": "A"
      },
      {
        "noteIdx": 30,
        "chord": "F"
      },
      {
        "noteIdx": 41,
        "chord": "A"
      },
      {
        "noteIdx": 52,
        "chord": "B"
      },
      {
        "noteIdx": 67,
        "chord": "C"
      },
      {
        "noteIdx": 69,
        "chord": "Em"
      },
      {
        "noteIdx": 71,
        "chord": "E"
      },
      {
        "noteIdx": 73,
        "chord": "Am"
      },
      {
        "noteIdx": 75,
        "chord": "Dm"
      },
      {
        "noteIdx": 90,
        "chord": "D"
      },
      {
        "noteIdx": 101,
        "chord": "D"
      },
      {
        "noteIdx": 103,
        "chord": "B"
      },
      {
        "noteIdx": 128,
        "chord": "E"
      }
    ]
  }
}
